bojpy/boj.py
bojpy/version.py
bojpy-0.0.1.dist-info/LICENSE
bojpy-0.0.1.dist-info/METADATA
bojpy-0.0.1.dist-info/WHEEL
bojpy-0.0.1.dist-info/top_level.txt
bojpy-0.0.1.dist-info/RECORD
