Metadata-Version: 2.1
Name: bojpy
Version: 0.0.1
Summary: Python Wrapper for the Bank of Japan (BOJ) Time-Series Data Search
Home-page: https://github.com/philsv/bojpy
Author: philsv
Author-email: frphsv@gmail.com
License: MIT
Keywords: boj,bank of japan,central bank,statistical data
Platform: UNKNOWN
Classifier: Development Status :: 2 - Pre-Alpha
Classifier: Intended Audience :: Developers
Classifier: Programming Language :: Python :: 3
Classifier: Programming Language :: Python :: 3.6
Classifier: Programming Language :: Python :: 3.7
Classifier: Programming Language :: Python :: 3.8
Classifier: Programming Language :: Python :: 3.9
Classifier: Programming Language :: Python :: 3.10
Classifier: Operating System :: Microsoft :: Windows
Classifier: Operating System :: Unix
Classifier: Operating System :: MacOS :: MacOS X
Classifier: License :: OSI Approved :: MIT License
Requires-Dist: pandas
Requires-Dist: requests
Requires-Dist: beautifulsoup4
